django_no_queryset_admin_actions/__init__.py
django_no_queryset_admin_actions/admin.py
django_no_queryset_admin_actions/apps.py
django_no_queryset_admin_actions/decorators.py
django_no_queryset_admin_actions/locale/de/LC_MESSAGES/django.mo
django_no_queryset_admin_actions/locale/de/LC_MESSAGES/django.po
django_no_queryset_admin_actions/locale/en/LC_MESSAGES/django.mo
django_no_queryset_admin_actions/locale/en/LC_MESSAGES/django.po
django_no_queryset_admin_actions/locale/es/LC_MESSAGES/django.mo
django_no_queryset_admin_actions/locale/es/LC_MESSAGES/django.po
django_no_queryset_admin_actions/locale/fr/LC_MESSAGES/django.mo
django_no_queryset_admin_actions/locale/fr/LC_MESSAGES/django.po
django_no_queryset_admin_actions/locale/it/LC_MESSAGES/django.mo
django_no_queryset_admin_actions/locale/it/LC_MESSAGES/django.po
django_no_queryset_admin_actions/locale/nl/LC_MESSAGES/django.mo
django_no_queryset_admin_actions/locale/nl/LC_MESSAGES/django.po
django_no_queryset_admin_actions/locale/pl/LC_MESSAGES/django.mo
django_no_queryset_admin_actions/locale/pl/LC_MESSAGES/django.po
django_no_queryset_admin_actions/locale/pt/LC_MESSAGES/django.mo
django_no_queryset_admin_actions/locale/pt/LC_MESSAGES/django.po
django_no_queryset_admin_actions/locale/ru/LC_MESSAGES/django.mo
django_no_queryset_admin_actions/locale/ru/LC_MESSAGES/django.po
django_no_queryset_admin_actions/locale/sv/LC_MESSAGES/django.mo
django_no_queryset_admin_actions/locale/sv/LC_MESSAGES/django.po
django_no_queryset_admin_actions-1.1.0.dist-info/LICENSE
django_no_queryset_admin_actions-1.1.0.dist-info/METADATA
django_no_queryset_admin_actions-1.1.0.dist-info/WHEEL
django_no_queryset_admin_actions-1.1.0.dist-info/top_level.txt
django_no_queryset_admin_actions-1.1.0.dist-info/RECORD
